rhino_shapely_interop/__init__.py
rhino_shapely_interop/importers.py
rhino_shapely_interop/rhino_wrappers.py
rhino_shapely_interop/transformations.py
rhino_shapley_interop-0.0.4.dist-info/LICENSE
rhino_shapley_interop-0.0.4.dist-info/METADATA
rhino_shapley_interop-0.0.4.dist-info/WHEEL
rhino_shapley_interop-0.0.4.dist-info/top_level.txt
rhino_shapley_interop-0.0.4.dist-info/RECORD
