Metadata-Version: 2.1
Name: rhino-shapley-interop
Version: 0.0.4
Summary: A python package for converting rhino geometry into shapely geometry
Home-page: https://github.com/normanrichardson/rhino_shapely_interop
Author: Norman JN Richardson
Author-email: normanrichardson@gmail.com
License: MIT License
Project-URL: Bug Tracker, https://github.com/normanrichardson/rhino_shapely_interop/issues
Platform: Any
Classifier: Programming Language :: Python :: 3
Classifier: License :: OSI Approved :: MIT License
Classifier: Operating System :: OS Independent
Requires-Python: >=3.6
License-File: LICENSE
Requires-Dist: numpy
Requires-Dist: rhino3dm
Requires-Dist: Shapely
Provides-Extra: dep
Requires-Dist: twine ; extra == 'dep'
Requires-Dist: build ; extra == 'dep'
Provides-Extra: dev
Requires-Dist: numpy (==1.21.1) ; extra == 'dev'
Requires-Dist: rhino3dm (==7.7.0) ; extra == 'dev'
Requires-Dist: Shapely (==1.8.0) ; extra == 'dev'
Requires-Dist: matplotlib ; extra == 'dev'
Requires-Dist: black ; extra == 'dev'
Requires-Dist: isort ; extra == 'dev'
Requires-Dist: flake8 ; extra == 'dev'
